{"cameraMode":{"drawMode":0,"name":"Shaded","section":"Shading Mode"},"sceneLighting":false,"audioPlay":false,"sceneViewState":{"showFog":true,"showMaterialUpdate":false,"showSkybox":false,"showFlares":true,"showImageEffects":true,"showParticleSystems":true},"in2DMode":false,"pivot":{"x":39.85930252075195,"y":-79.52062225341797,"z":92.06149291992188},"rotation":{"x":-0.2961070239543915,"y":-0.5168710947036743,"z":0.19650380313396455,"w":-0.7788411974906921},"size":14.282856941223145,"orthographic":false}